eurocodepy/__init__.py
eurocodepy/dbase.py
eurocodepy/national_parameters.py
eurocodepy/data/chs_profiles_euro.json
eurocodepy/data/eurocode_data_portugal.csv
eurocodepy/data/eurocode_data_portugal.xlsx
eurocodepy/data/eurocodes.json
eurocodepy/data/i_profiles_euro.json
eurocodepy/data/rhs_profiles_euro.json
eurocodepy/data/shs_profiles_euro.json
eurocodepy/ec1/__init__.py
eurocodepy/ec1/combos.py
eurocodepy/ec1/snow/__init__.py
eurocodepy/ec1/wind/__init__.py
eurocodepy/ec1/wind/pressure.py
eurocodepy/ec2/__init__.py
eurocodepy/ec2/materials.py
eurocodepy/ec2/fire/__init__.py
eurocodepy/ec2/fire/fire_base.py
eurocodepy/ec2/sls/__init__.py
eurocodepy/ec2/sls/crack.py
eurocodepy/ec2/sls/creep.py
eurocodepy/ec2/sls/shrinkage.py
eurocodepy/ec2/uls/__init__.py
eurocodepy/ec2/uls/beam.py
eurocodepy/ec2/uls/bend_circ.py
eurocodepy/ec2/uls/punch.py
eurocodepy/ec2/uls/shear.py
eurocodepy/ec2/uls/shell.py
eurocodepy/ec3/__init__.py
eurocodepy/ec3/uls/__init__.py
eurocodepy/ec5/__init__.py
eurocodepy/ec5/materials.py
eurocodepy/ec5/sls/__init__.py
eurocodepy/ec5/sls/deformation.py
eurocodepy/ec5/sls/vibration.py
eurocodepy/ec7/__init__.py
eurocodepy/ec7/bearing_capacity.py
eurocodepy/ec7/earth_pressures.py
eurocodepy/ec7/materials.py
eurocodepy/ec8/__init__.py
eurocodepy/ec8/spectrum.py
eurocodepy/utils/__init__.py
eurocodepy/utils/section_properties.py
eurocodepy/utils/stress.py
eurocodepy-2025.12.1.dist-info/licenses/LICENSE.md
eurocodepy-2025.12.1.dist-info/METADATA
eurocodepy-2025.12.1.dist-info/WHEEL
eurocodepy-2025.12.1.dist-info/top_level.txt
eurocodepy-2025.12.1.dist-info/RECORD
