Metadata-Version: 2.4
Name: eurocodepy
Version: 2025.12.1
Summary: A package for eurocode calculations
Author-email: Paulo Cachim <pcachim@ua.pt>
Project-URL: Homepage, https://github.com/pcachim/eurocodepy
Project-URL: Bug Tracker, https://github.com/pcachim/eurocodepy/issues
Classifier: Programming Language :: Python :: 3
Classifier: License :: OSI Approved :: MIT License
Classifier: Operating System :: OS Independent
Requires-Python: >=3.9
License-File: LICENSE.md
Requires-Dist: matplotlib>=3.9.4
Requires-Dist: numpy>=2.0.2
Requires-Dist: pandas>=2.2.3
Requires-Dist: plotly>=6.1.2
Requires-Dist: mkdocs>=1.6.1
Requires-Dist: mkdocs-material>=9.6.14
Requires-Dist: mkdocstrings>=0.29.1
Requires-Dist: mkdocstrings-python>=1.16.12
Requires-Dist: mkdocs-gen-files>=0.5.0
Requires-Dist: mkdocs-literate-nav>=0.6.2
Requires-Dist: mkdocs-section-index>=0.3.10
Provides-Extra: dev
Requires-Dist: ruff>=0.11.13; extra == "dev"
Requires-Dist: ty>=0.0.1a10; extra == "dev"
Requires-Dist: pre-commit>=4.2.0; extra == "dev"
Dynamic: license-file
